quant_performance/__init__.py
quant_performance/report.py
quant_performance/version.py
quant_performance-0.0.1.dist-info/LICENSE
quant_performance-0.0.1.dist-info/METADATA
quant_performance-0.0.1.dist-info/WHEEL
quant_performance-0.0.1.dist-info/entry_points.txt
quant_performance-0.0.1.dist-info/top_level.txt
quant_performance-0.0.1.dist-info/RECORD
