Metadata-Version: 2.1
Name: quant-performance
Version: 0.0.1
Summary: This is a package for calculating performance metrics for quantitative finance
Home-page: https://github.com/amirnajafi/quantperf
Author: Amir najafi
Author-email: contact@amirnajafi.com
License: MIT License
Keywords: quant algotrading algorithmic-trading quantitative-trading quantitative-analysis algo-trading visualization plotting
Platform: any
Classifier: Development Status :: 5 - Production/Stable
Classifier: Operating System :: OS Independent
Classifier: Intended Audience :: Developers
Classifier: Intended Audience :: Financial and Insurance Industry
Classifier: Intended Audience :: Science/Research
Classifier: Topic :: Office/Business :: Financial
Classifier: Topic :: Office/Business :: Financial :: Investment
Classifier: Topic :: Software Development :: Libraries
Classifier: Topic :: Software Development :: Libraries :: Python Modules
Classifier: Topic :: Scientific/Engineering
Classifier: Topic :: Scientific/Engineering :: Information Analysis
Classifier: Topic :: Scientific/Engineering :: Mathematics
Classifier: Programming Language :: Python :: 3.6
Classifier: Programming Language :: Python :: 3.7
Classifier: Programming Language :: Python :: 3.8
Classifier: Programming Language :: Python :: 3.9
License-File: LICENSE
Requires-Dist: numpy (==1.22.2)
Requires-Dist: pandas (==1.4.1)
